packagePepe/__init__.py
packagePepe/cpp_functions.cp312-win_amd64.pyd
packagePepe/module_cpp.cp312-win_amd64.pyd
packagePepe/pepe.py
packagePepe/pepe_cpp.cp312-win_amd64.pyd
packagePepe/wrapper.py
pepe/__init__.py
pepe/pepe.py
pepe/pepe_cpp.cp312-win_amd64.pyd
packagePepe-0.1.7.dist-info/METADATA
packagePepe-0.1.7.dist-info/WHEEL
packagePepe-0.1.7.dist-info/top_level.txt
packagePepe-0.1.7.dist-info/RECORD
