Metadata-Version: 2.1
Name: packagePepe
Version: 0.1.7
Summary: Mi primer paquete con C++ y Python
Author: Tu Nombre
Author-email: tu_email@example.com
